Metadata-Version: 2.1
Name: utils4file
Version: 1.0.7
Summary: File b64 encode and decode , keep md5 consist in procedure
Author: chenfengshf
Author-email: chenfengshf@hotmail.com
